[{"s": "-", "l": {"s": "*", "l": {"s": "C"}, "r": {"s": "X_1"}}, "r": {"s": "X_0"}}, {"s": "+", "l": {"s": "*", "l": {"s": "X_1"}, "r": {"s": "X_0"}}, "r": {"s": "exp", "l": {"s": "/", "l": {"s": "C"}, "r": {"s": "X_0"}}}}, {"s": "-", "l": {"s": "/", "l": {"s": "X_0"}, "r": {"s": "X_1"}}, "r": {"s": "/", "l": {"s": "*", "l": {"s": "C"}, "r": {"s": "X_1"}}, "r": {"s": "X_1"}}}, {"s": "*", "l": {"s": "*", "l": {"s": "*", "l": {"s": "C"}, "r": {"s": "+", "l": {"s": "/", "l": {"s": "X_1"}, "r": {"s": "X_1"}}, "r": {"s": "X_0"}}}, "r": {"s": "X_0"}}, "r": {"s": "X_0"}}, {"s": "*", "l": {"s": "*", "l": {"s": "exp", "l": {"s": "/", "l": {"s": "*", "l": {"s": "X_1"}, "r": {"s": "X_1"}}, "r": {"s": "X_0"}}}, "r": {"s": "X_0"}}, "r": {"s": "C"}}, {"s": "/", "l": {"s": "sin", "l": {"s": "-", "l": {"s": "+", "l": {"s": "X_1"}, "r": {"s": "X_0"}}, "r": {"s": "X_1"}}}, "r": {"s": "C"}}, {"s": "+", "l": {"s": "-", "l": {"s": "/", "l": {"s": "X_0"}, "r": {"s": "X_0"}}, "r": {"s": "*", "l": {"s": "C"}, "r": {"s": "X_1"}}}, "r": {"s": "X_0"}}, {"s": "+", "l": {"s": "-", "l": {"s": "-", "l": {"s": "/", "l": {"s": "X_1"}, "r": {"s": "X_0"}}, "r": {"s": "*", "l": {"s": "*", "l": {"s": "X_0"}, "r": {"s": "X_1"}}, "r": {"s": "X_0"}}}, "r": {"s": "*", "l": {"s": "X_1"}, "r": {"s": "X_1"}}}, "r": {"s": "X_1"}}, {"s": "*", "l": {"s": "*", "l": {"s": "*", "l": {"s": "X_0"}, "r": {"s": "X_0"}}, "r": {"s": "+", "l": {"s": "X_1"}, "r": {"s": "X_0"}}}, "r": {"s": "X_1"}}, {"s": "-", "l": {"s": "X_0"}, "r": {"s": "*", "l": {"s": "sqrt", "l": {"s": "X_1"}}, "r": {"s": "X_1"}}}, {"s": "+", "l": {"s": "/", "l": {"s": "X_1"}, "r": {"s": "X_1"}}, "r": {"s": "*", "l": {"s": "exp", "l": {"s": "*", "l": {"s": "*", "l": {"s": "X_1"}, "r": {"s": "C"}}, "r": {"s": "X_0"}}}, "r": {"s": "X_0"}}}, {"s": "*", "l": {"s": "X_0"}, "r": {"s": "/", "l": {"s": "/", "l": {"s": "*", "l": {"s": "*", "l": {"s": "X_0"}, "r": {"s": "C"}}, "r": {"s": "X_0"}}, "r": {"s": "X_1"}}, "r": {"s": "X_0"}}}, {"s": "+", "l": {"s": "+", "l": {"s": "+", "l": {"s": "X_0"}, "r": {"s": "X_0"}}, "r": {"s": "X_1"}}, "r": {"s": "X_0"}}, {"s": "+", "l": {"s": "X_1"}, "r": {"s": "*", "l": {"s": "*", "l": {"s": "*", "l": {"s": "*", "l": {"s": "X_1"}, "r": {"s": "X_0"}}, "r": {"s": "X_0"}}, "r": {"s": "X_1"}}, "r": {"s": "X_0"}}}, {"s": "*", "l": {"s": "*", "l": {"s": "/", "l": {"s": "X_1"}, "r": {"s": "X_0"}}, "r": {"s": "sqrt", "l": {"s": "+", "l": {"s": "*", "l": {"s": "X_0"}, "r": {"s": "X_0"}}, "r": {"s": "X_0"}}}}, "r": {"s": "C"}}, {"s": "*", "l": {"s": "/", "l": {"s": "/", "l": {"s": "C"}, "r": {"s": "*", "l": {"s": "*", "l": {"s": "C"}, "r": {"s": "X_0"}}, "r": {"s": "/", "l": {"s": "X_0"}, "r": {"s": "X_1"}}}}, "r": {"s": "X_1"}}, "r": {"s": "C"}}, {"s": "-", "l": {"s": "*", "l": {"s": "*", "l": {"s": "*", "l": {"s": "X_1"}, "r": {"s": "X_1"}}, "r": {"s": "X_1"}}, "r": {"s": "exp", "l": {"s": "+", "l": {"s": "/", "l": {"s": "X_0"}, "r": {"s": "X_0"}}, "r": {"s": "X_1"}}}}, "r": {"s": "X_1"}}, {"s": "*", "l": {"s": "*", "l": {"s": "*", "l": {"s": "*", "l": {"s": "X_1"}, "r": {"s": "C"}}, "r": {"s": "X_0"}}, "r": {"s": "X_1"}}, "r": {"s": "X_1"}}, {"s": "-", "l": {"s": "+", "l": {"s": "-", "l": {"s": "C"}, "r": {"s": "X_0"}}, "r": {"s": "*", "l": {"s": "X_1"}, "r": {"s": "X_1"}}}, "r": {"s": "*", "l": {"s": "X_0"}, "r": {"s": "X_1"}}}, {"s": "+", "l": {"s": "+", "l": {"s": "*", "l": {"s": "C"}, "r": {"s": "X_0"}}, "r": {"s": "X_1"}}, "r": {"s": "X_0"}}, {"s": "-", "l": {"s": "+", "l": {"s": "X_1"}, "r": {"s": "*", "l": {"s": "*", "l": {"s": "*", "l": {"s": "X_1"}, "r": {"s": "X_0"}}, "r": {"s": "X_0"}}, "r": {"s": "X_0"}}}, "r": {"s": "*", "l": {"s": "X_1"}, "r": {"s": "X_0"}}}, {"s": "-", "l": {"s": "*", "l": {"s": "/", "l": {"s": "X_0"}, "r": {"s": "C"}}, "r": {"s": "X_1"}}, "r": {"s": "X_0"}}, {"s": "+", "l": {"s": "+", "l": {"s": "-", "l": {"s": "/", "l": {"s": "X_0"}, "r": {"s": "X_0"}}, "r": {"s": "*", "l": {"s": "X_1"}, "r": {"s": "X_1"}}}, "r": {"s": "*", "l": {"s": "*", "l": {"s": "X_1"}, "r": {"s": "X_1"}}, "r": {"s": "C"}}}, "r": {"s": "exp", "l": {"s": "X_1"}}}, {"s": "/", "l": {"s": "+", "l": {"s": "*", "l": {"s": "X_0"}, "r": {"s": "cos", "l": {"s": "X_0"}}}, "r": {"s": "X_0"}}, "r": {"s": "X_1"}}, {"s": "*", "l": {"s": "/", "l": {"s": "X_0"}, "r": {"s": "X_1"}}, "r": {"s": "C"}}, {"s": "+", "l": {"s": "*", "l": {"s": "/", "l": {"s": "X_1"}, "r": {"s": "C"}}, "r": {"s": "C"}}, "r": {"s": "*", "l": {"s": "*", "l": {"s": "*", "l": {"s": "X_1"}, "r": {"s": "X_0"}}, "r": {"s": "X_1"}}, "r": {"s": "C"}}}, {"s": "+", "l": {"s": "*", "l": {"s": "*", "l": {"s": "C"}, "r": {"s": "sqrt", "l": {"s": "X_1"}}}, "r": {"s": "X_0"}}, "r": {"s": "/", "l": {"s": "X_0"}, "r": {"s": "X_1"}}}, {"s": "*", "l": {"s": "+", "l": {"s": "X_1"}, "r": {"s": "*", "l": {"s": "/", "l": {"s": "*", "l": {"s": "X_1"}, "r": {"s": "X_1"}}, "r": {"s": "X_0"}}, "r": {"s": "X_0"}}}, "r": {"s": "sqrt", "l": {"s": "+", "l": {"s": "*", "l": {"s": "X_0"}, "r": {"s": "X_0"}}, "r": {"s": "X_1"}}}}, {"s": "-", "l": {"s": "+", "l": {"s": "+", "l": {"s": "X_1"}, "r": {"s": "*", "l": {"s": "X_0"}, "r": {"s": "C"}}}, "r": {"s": "X_0"}}, "r": {"s": "*", "l": {"s": "C"}, "r": {"s": "X_1"}}}, {"s": "+", "l": {"s": "/", "l": {"s": "X_0"}, "r": {"s": "C"}}, "r": {"s": "*", "l": {"s": "X_1"}, "r": {"s": "/", "l": {"s": "-", "l": {"s": "X_1"}, "r": {"s": "*", "l": {"s": "C"}, "r": {"s": "X_1"}}}, "r": {"s": "C"}}}}, {"s": "-", "l": {"s": "-", "l": {"s": "*", "l": {"s": "X_1"}, "r": {"s": "X_1"}}, "r": {"s": "/", "l": {"s": "X_0"}, "r": {"s": "X_0"}}}, "r": {"s": "X_1"}}, {"s": "/", "l": {"s": "X_1"}, "r": {"s": "sin", "l": {"s": "+", "l": {"s": "X_0"}, "r": {"s": "X_1"}}}}, {"s": "+", "l": {"s": "+", "l": {"s": "*", "l": {"s": "*", "l": {"s": "X_1"}, "r": {"s": "X_1"}}, "r": {"s": "C"}}, "r": {"s": "*", "l": {"s": "X_1"}, "r": {"s": "X_0"}}}, "r": {"s": "X_0"}}, {"s": "-", "l": {"s": "*", "l": {"s": "*", "l": {"s": "*", "l": {"s": "X_1"}, "r": {"s": "C"}}, "r": {"s": "C"}}, "r": {"s": "X_1"}}, "r": {"s": "*", "l": {"s": "*", "l": {"s": "*", "l": {"s": "X_0"}, "r": {"s": "X_0"}}, "r": {"s": "X_0"}}, "r": {"s": "X_1"}}}, {"s": "-", "l": {"s": "*", "l": {"s": "/", "l": {"s": "X_0"}, "r": {"s": "X_0"}}, "r": {"s": "X_1"}}, "r": {"s": "X_1"}}, {"s": "*", "l": {"s": "/", "l": {"s": "*", "l": {"s": "*", "l": {"s": "C"}, "r": {"s": "X_0"}}, "r": {"s": "X_1"}}, "r": {"s": "X_0"}}, "r": {"s": "X_0"}}, {"s": "*", "l": {"s": "X_1"}, "r": {"s": "sqrt", "l": {"s": "/", "l": {"s": "*", "l": {"s": "X_1"}, "r": {"s": "X_0"}}, "r": {"s": "X_1"}}}}, {"s": "*", "l": {"s": "/", "l": {"s": "/", "l": {"s": "X_1"}, "r": {"s": "X_0"}}, "r": {"s": "/", "l": {"s": "X_1"}, "r": {"s": "X_0"}}}, "r": {"s": "X_1"}}, {"s": "+", "l": {"s": "+", "l": {"s": "*", "l": {"s": "*", "l": {"s": "*", "l": {"s": "X_0"}, "r": {"s": "X_0"}}, "r": {"s": "X_0"}}, "r": {"s": "^2", "l": {"s": "X_1"}}}, "r": {"s": "sqrt", "l": {"s": "C"}}}, "r": {"s": "*", "l": {"s": "*", "l": {"s": "*", "l": {"s": "X_1"}, "r": {"s": "X_0"}}, "r": {"s": "X_1"}}, "r": {"s": "C"}}}, {"s": "+", "l": {"s": "+", "l": {"s": "*", "l": {"s": "/", "l": {"s": "X_0"}, "r": {"s": "X_0"}}, "r": {"s": "X_0"}}, "r": {"s": "*", "l": {"s": "X_0"}, "r": {"s": "X_1"}}}, "r": {"s": "X_1"}}, {"s": "+", "l": {"s": "-", "l": {"s": "*", "l": {"s": "X_1"}, "r": {"s": "X_1"}}, "r": {"s": "X_0"}}, "r": {"s": "*", "l": {"s": "X_0"}, "r": {"s": "X_0"}}}, {"s": "-", "l": {"s": "log", "l": {"s": "+", "l": {"s": "X_1"}, "r": {"s": "C"}}}, "r": {"s": "*", "l": {"s": "*", "l": {"s": "X_0"}, "r": {"s": "X_1"}}, "r": {"s": "X_0"}}}, {"s": "/", "l": {"s": "*", "l": {"s": "log", "l": {"s": "*", "l": {"s": "X_0"}, "r": {"s": "X_1"}}}, "r": {"s": "X_1"}}, "r": {"s": "X_0"}}, {"s": "*", "l": {"s": "+", "l": {"s": "*", "l": {"s": "*", "l": {"s": "*", "l": {"s": "X_0"}, "r": {"s": "X_0"}}, "r": {"s": "X_1"}}, "r": {"s": "X_0"}}, "r": {"s": "X_1"}}, "r": {"s": "X_0"}}, {"s": "*", "l": {"s": "*", "l": {"s": "exp", "l": {"s": "+", "l": {"s": "*", "l": {"s": "X_0"}, "r": {"s": "X_1"}}, "r": {"s": "X_1"}}}, "r": {"s": "X_0"}}, "r": {"s": "X_1"}}, {"s": "/", "l": {"s": "*", "l": {"s": "/", "l": {"s": "*", "l": {"s": "X_1"}, "r": {"s": "X_1"}}, "r": {"s": "X_1"}}, "r": {"s": "X_1"}}, "r": {"s": "*", "l": {"s": "X_0"}, "r": {"s": "X_0"}}}, {"s": "-", "l": {"s": "+", "l": {"s": "X_1"}, "r": {"s": "X_0"}}, "r": {"s": "*", "l": {"s": "/", "l": {"s": "X_1"}, "r": {"s": "X_1"}}, "r": {"s": "X_0"}}}, {"s": "-", "l": {"s": "+", "l": {"s": "/", "l": {"s": "X_0"}, "r": {"s": "X_0"}}, "r": {"s": "exp", "l": {"s": "X_0"}}}, "r": {"s": "X_1"}}, {"s": "+", "l": {"s": "+", "l": {"s": "/", "l": {"s": "C"}, "r": {"s": "C"}}, "r": {"s": "X_1"}}, "r": {"s": "exp", "l": {"s": "X_1"}}}, {"s": "+", "l": {"s": "X_0"}, "r": {"s": "*", "l": {"s": "*", "l": {"s": "/", "l": {"s": "X_1"}, "r": {"s": "X_0"}}, "r": {"s": "X_1"}}, "r": {"s": "X_1"}}}, {"s": "-", "l": {"s": "*", "l": {"s": "*", "l": {"s": "C"}, "r": {"s": "/", "l": {"s": "*", "l": {"s": "X_1"}, "r": {"s": "X_0"}}, "r": {"s": "X_1"}}}, "r": {"s": "C"}}, "r": {"s": "*", "l": {"s": "X_0"}, "r": {"s": "C"}}}, {"s": "+", "l": {"s": "X_0"}, "r": {"s": "*", "l": {"s": "*", "l": {"s": "*", "l": {"s": "X_0"}, "r": {"s": "X_0"}}, "r": {"s": "X_1"}}, "r": {"s": "C"}}}, {"s": "*", "l": {"s": "*", "l": {"s": "/", "l": {"s": "X_1"}, "r": {"s": "+", "l": {"s": "sqrt", "l": {"s": "X_0"}}, "r": {"s": "X_0"}}}, "r": {"s": "X_0"}}, "r": {"s": "C"}}, {"s": "/", "l": {"s": "/", "l": {"s": "*", "l": {"s": "*", "l": {"s": "*", "l": {"s": "X_0"}, "r": {"s": "X_0"}}, "r": {"s": "X_1"}}, "r": {"s": "cos", "l": {"s": "X_0"}}}, "r": {"s": "X_0"}}, "r": {"s": "+", "l": {"s": "+", "l": {"s": "X_1"}, "r": {"s": "X_0"}}, "r": {"s": "X_1"}}}, {"s": "-", "l": {"s": "*", "l": {"s": "X_0"}, "r": {"s": "X_1"}}, "r": {"s": "/", "l": {"s": "X_1"}, "r": {"s": "X_1"}}}, {"s": "-", "l": {"s": "*", "l": {"s": "X_0"}, "r": {"s": "X_1"}}, "r": {"s": "*", "l": {"s": "*", "l": {"s": "X_1"}, "r": {"s": "X_0"}}, "r": {"s": "X_0"}}}, {"s": "+", "l": {"s": "-", "l": {"s": "-", "l": {"s": "X_0"}, "r": {"s": "*", "l": {"s": "*", "l": {"s": "X_0"}, "r": {"s": "X_0"}}, "r": {"s": "X_0"}}}, "r": {"s": "*", "l": {"s": "X_0"}, "r": {"s": "X_0"}}}, "r": {"s": "*", "l": {"s": "C"}, "r": {"s": "X_1"}}}, {"s": "*", "l": {"s": "/", "l": {"s": "*", "l": {"s": "C"}, "r": {"s": "X_1"}}, "r": {"s": "X_1"}}, "r": {"s": "-", "l": {"s": "X_0"}, "r": {"s": "X_1"}}}, {"s": "+", "l": {"s": "X_0"}, "r": {"s": "/", "l": {"s": "X_1"}, "r": {"s": "-", "l": {"s": "X_1"}, "r": {"s": "*", "l": {"s": "X_1"}, "r": {"s": "X_1"}}}}}, {"s": "+", "l": {"s": "+", "l": {"s": "C"}, "r": {"s": "X_0"}}, "r": {"s": "C"}}, {"s": "+", "l": {"s": "*", "l": {"s": "X_0"}, "r": {"s": "C"}}, "r": {"s": "/", "l": {"s": "X_1"}, "r": {"s": "X_1"}}}, {"s": "*", "l": {"s": "X_0"}, "r": {"s": "exp", "l": {"s": "X_1"}}}, {"s": "*", "l": {"s": "+", "l": {"s": "*", "l": {"s": "X_1"}, "r": {"s": "C"}}, "r": {"s": "X_1"}}, "r": {"s": "/", "l": {"s": "X_1"}, "r": {"s": "X_0"}}}, {"s": "*", "l": {"s": "*", "l": {"s": "*", "l": {"s": "*", "l": {"s": "X_0"}, "r": {"s": "X_1"}}, "r": {"s": "X_0"}}, "r": {"s": "X_0"}}, "r": {"s": "C"}}, {"s": "+", "l": {"s": "exp", "l": {"s": "+", "l": {"s": "X_1"}, "r": {"s": "*", "l": {"s": "X_0"}, "r": {"s": "C"}}}}, "r": {"s": "/", "l": {"s": "*", "l": {"s": "X_1"}, "r": {"s": "X_1"}}, "r": {"s": "X_0"}}}, {"s": "+", "l": {"s": "-", "l": {"s": "*", "l": {"s": "/", "l": {"s": "C"}, "r": {"s": "C"}}, "r": {"s": "X_0"}}, "r": {"s": "X_1"}}, "r": {"s": "*", "l": {"s": "*", "l": {"s": "X_1"}, "r": {"s": "C"}}, "r": {"s": "X_1"}}}, {"s": "+", "l": {"s": "+", "l": {"s": "X_0"}, "r": {"s": "/", "l": {"s": "*", "l": {"s": "X_1"}, "r": {"s": "C"}}, "r": {"s": "C"}}}, "r": {"s": "X_0"}}, {"s": "+", "l": {"s": "-", "l": {"s": "sin", "l": {"s": "+", "l": {"s": "/", "l": {"s": "X_0"}, "r": {"s": "C"}}, "r": {"s": "X_0"}}}, "r": {"s": "*", "l": {"s": "/", "l": {"s": "X_0"}, "r": {"s": "X_1"}}, "r": {"s": "C"}}}, "r": {"s": "*", "l": {"s": "X_0"}, "r": {"s": "X_1"}}}, {"s": "-", "l": {"s": "/", "l": {"s": "*", "l": {"s": "X_0"}, "r": {"s": "C"}}, "r": {"s": "X_0"}}, "r": {"s": "X_0"}}, {"s": "+", "l": {"s": "X_0"}, "r": {"s": "+", "l": {"s": "*", "l": {"s": "C"}, "r": {"s": "X_0"}}, "r": {"s": "*", "l": {"s": "-", "l": {"s": "/", "l": {"s": "X_1"}, "r": {"s": "X_0"}}, "r": {"s": "*", "l": {"s": "X_1"}, "r": {"s": "X_1"}}}, "r": {"s": "X_0"}}}}, {"s": "*", "l": {"s": "X_0"}, "r": {"s": "*", "l": {"s": "*", "l": {"s": "C"}, "r": {"s": "X_1"}}, "r": {"s": "C"}}}, {"s": "+", "l": {"s": "sqrt", "l": {"s": "X_1"}}, "r": {"s": "*", "l": {"s": "X_1"}, "r": {"s": "X_0"}}}, {"s": "+", "l": {"s": "/", "l": {"s": "/", "l": {"s": "X_1"}, "r": {"s": "X_1"}}, "r": {"s": "cos", "l": {"s": "*", "l": {"s": "-", "l": {"s": "C"}, "r": {"s": "X_0"}}, "r": {"s": "X_1"}}}}, "r": {"s": "X_0"}}, {"s": "+", "l": {"s": "*", "l": {"s": "*", "l": {"s": "exp", "l": {"s": "*", "l": {"s": "X_0"}, "r": {"s": "X_1"}}}, "r": {"s": "X_0"}}, "r": {"s": "X_0"}}, "r": {"s": "*", "l": {"s": "sin", "l": {"s": "*", "l": {"s": "*", "l": {"s": "X_1"}, "r": {"s": "X_1"}}, "r": {"s": "X_1"}}}, "r": {"s": "X_1"}}}, {"s": "*", "l": {"s": "*", "l": {"s": "X_0"}, "r": {"s": "X_1"}}, "r": {"s": "+", "l": {"s": "*", "l": {"s": "X_0"}, "r": {"s": "sin", "l": {"s": "C"}}}, "r": {"s": "C"}}}, {"s": "+", "l": {"s": "*", "l": {"s": "X_0"}, "r": {"s": "C"}}, "r": {"s": "*", "l": {"s": "*", "l": {"s": "/", "l": {"s": "X_0"}, "r": {"s": "X_1"}}, "r": {"s": "X_0"}}, "r": {"s": "X_1"}}}, {"s": "*", "l": {"s": "*", "l": {"s": "X_1"}, "r": {"s": "X_1"}}, "r": {"s": "C"}}, {"s": "+", "l": {"s": "+", "l": {"s": "X_0"}, "r": {"s": "exp", "l": {"s": "X_1"}}}, "r": {"s": "X_0"}}, {"s": "+", "l": {"s": "+", "l": {"s": "+", "l": {"s": "+", "l": {"s": "X_1"}, "r": {"s": "*", "l": {"s": "X_0"}, "r": {"s": "X_0"}}}, "r": {"s": "X_0"}}, "r": {"s": "sqrt", "l": {"s": "*", "l": {"s": "/", "l": {"s": "X_0"}, "r": {"s": "X_0"}}, "r": {"s": "X_0"}}}}, "r": {"s": "*", "l": {"s": "*", "l": {"s": "C"}, "r": {"s": "X_0"}}, "r": {"s": "X_0"}}}, {"s": "+", "l": {"s": "+", "l": {"s": "X_0"}, "r": {"s": "X_1"}}, "r": {"s": "*", "l": {"s": "/", "l": {"s": "X_0"}, "r": {"s": "X_0"}}, "r": {"s": "C"}}}, {"s": "+", "l": {"s": "+", "l": {"s": "X_0"}, "r": {"s": "X_0"}}, "r": {"s": "X_0"}}, {"s": "-", "l": {"s": "*", "l": {"s": "X_0"}, "r": {"s": "X_0"}}, "r": {"s": "/", "l": {"s": "X_0"}, "r": {"s": "X_1"}}}, {"s": "*", "l": {"s": "*", "l": {"s": "*", "l": {"s": "/", "l": {"s": "C"}, "r": {"s": "X_0"}}, "r": {"s": "X_1"}}, "r": {"s": "X_0"}}, "r": {"s": "X_1"}}, {"s": "+", "l": {"s": "X_1"}, "r": {"s": "*", "l": {"s": "*", "l": {"s": "*", "l": {"s": "*", "l": {"s": "C"}, "r": {"s": "X_1"}}, "r": {"s": "C"}}, "r": {"s": "X_0"}}, "r": {"s": "cos", "l": {"s": "C"}}}}, {"s": "+", "l": {"s": "X_0"}, "r": {"s": "/", "l": {"s": "*", "l": {"s": "X_0"}, "r": {"s": "C"}}, "r": {"s": "X_1"}}}, {"s": "cos", "l": {"s": "+", "l": {"s": "/", "l": {"s": "*", "l": {"s": "C"}, "r": {"s": "C"}}, "r": {"s": "X_1"}}, "r": {"s": "X_0"}}}, {"s": "*", "l": {"s": "/", "l": {"s": "*", "l": {"s": "X_0"}, "r": {"s": "X_1"}}, "r": {"s": "C"}}, "r": {"s": "C"}}, {"s": "-", "l": {"s": "/", "l": {"s": "/", "l": {"s": "*", "l": {"s": "X_1"}, "r": {"s": "X_0"}}, "r": {"s": "X_1"}}, "r": {"s": "X_0"}}, "r": {"s": "C"}}, {"s": "+", "l": {"s": "X_1"}, "r": {"s": "/", "l": {"s": "*", "l": {"s": "*", "l": {"s": "C"}, "r": {"s": "X_1"}}, "r": {"s": "X_0"}}, "r": {"s": "X_1"}}}, {"s": "+", "l": {"s": "X_0"}, "r": {"s": "*", "l": {"s": "*", "l": {"s": "/", "l": {"s": "X_1"}, "r": {"s": "X_1"}}, "r": {"s": "X_0"}}, "r": {"s": "X_1"}}}, {"s": "/", "l": {"s": "/", "l": {"s": "*", "l": {"s": "/", "l": {"s": "*", "l": {"s": "C"}, "r": {"s": "X_0"}}, "r": {"s": "X_1"}}, "r": {"s": "C"}}, "r": {"s": "X_0"}}, "r": {"s": "*", "l": {"s": "*", "l": {"s": "X_0"}, "r": {"s": "X_0"}}, "r": {"s": "sqrt", "l": {"s": "*", "l": {"s": "X_1"}, "r": {"s": "C"}}}}}, {"s": "+", "l": {"s": "X_1"}, "r": {"s": "*", "l": {"s": "*", "l": {"s": "X_0"}, "r": {"s": "X_1"}}, "r": {"s": "C"}}}, {"s": "+", "l": {"s": "+", "l": {"s": "+", "l": {"s": "*", "l": {"s": "*", "l": {"s": "X_1"}, "r": {"s": "X_1"}}, "r": {"s": "X_1"}}, "r": {"s": "X_0"}}, "r": {"s": "X_0"}}, "r": {"s": "/", "l": {"s": "X_1"}, "r": {"s": "X_0"}}}, {"s": "*", "l": {"s": "*", "l": {"s": "/", "l": {"s": "X_1"}, "r": {"s": "C"}}, "r": {"s": "*", "l": {"s": "C"}, "r": {"s": "X_0"}}}, "r": {"s": "X_1"}}, {"s": "*", "l": {"s": "X_0"}, "r": {"s": "cos", "l": {"s": "+", "l": {"s": "X_0"}, "r": {"s": "X_1"}}}}, {"s": "sqrt", "l": {"s": "*", "l": {"s": "sqrt", "l": {"s": "X_1"}}, "r": {"s": "C"}}}, {"s": "+", "l": {"s": "/", "l": {"s": "*", "l": {"s": "X_0"}, "r": {"s": "X_1"}}, "r": {"s": "X_1"}}, "r": {"s": "X_0"}}, {"s": "*", "l": {"s": "*", "l": {"s": "*", "l": {"s": "*", "l": {"s": "X_1"}, "r": {"s": "X_1"}}, "r": {"s": "C"}}, "r": {"s": "X_1"}}, "r": {"s": "X_0"}}, {"s": "+", "l": {"s": "*", "l": {"s": "*", "l": {"s": "*", "l": {"s": "C"}, "r": {"s": "X_0"}}, "r": {"s": "X_0"}}, "r": {"s": "X_0"}}, "r": {"s": "*", "l": {"s": "*", "l": {"s": "*", "l": {"s": "X_1"}, "r": {"s": "X_1"}}, "r": {"s": "sin", "l": {"s": "X_0"}}}, "r": {"s": "X_1"}}}, {"s": "/", "l": {"s": "*", "l": {"s": "*", "l": {"s": "*", "l": {"s": "X_1"}, "r": {"s": "X_1"}}, "r": {"s": "X_1"}}, "r": {"s": "X_0"}}, "r": {"s": "X_1"}}]